Compiled from "ch1_2.java"
public class ch1_2.ch1_2 {
  public ch1_2.ch1_2();
    Code:
       0: aload_0
       1: invokespecial #1                  // Method java/lang/Object."<init>":()V
       4: return

  public static void content();
    Code:
       0: new           #2                  // class java/util/Scanner
       3: dup
       4: getstatic     #3                  // Field java/lang/System.in:Ljava/io/InputStream;
       7: invokespecial #4                  // Method java/util/Scanner."<init>":(Ljava/io/InputStream;)V
      10: astore_0
      11: getstatic     #5                  // Field java/lang/System.out:Ljava/io/PrintStream;
      14: ldc           #6                  // String ½Ð¿é¤J©m¦W:
      16: invokevirtual #7                  // Method java/io/PrintStream.println:(Ljava/lang/String;)V
      19: aload_0
      20: invokevirtual #8                  // Method java/util/Scanner.next:()Ljava/lang/String;
      23: astore_1
      24: getstatic     #5                  // Field java/lang/System.out:Ljava/io/PrintStream;
      27: aload_1
      28: invokedynamic #9,  0              // InvokeDynamic #0:makeConcatWithConstants:(Ljava/lang/String;)Ljava/lang/String;
      33: invokevirtual #7                  // Method java/io/PrintStream.println:(Ljava/lang/String;)V
      36: aload_0
      37: invokevirtual #10                 // Method java/util/Scanner.close:()V
      40: return
}
